{
    "calendar_year": 2024,
    "months": [
      {
        "header_text": "Januar",
        "cell_count_per_row": 7,
        "row_count": 5,
        "border_style": "border_style_curved_corners",
        "table_content": [
          ["Mo", "Di", "Mi", "Do", "Fr", "Sa", "So"],
          ["1", "2", "3", "4", "5", "6", "7"],
          ["8", "9", "10", "11", "12", "13", "14"],
          ["15", "16", "17", "18", "19", "20", "21"],
          ["22", "23", "24", "25", "26", "27", "28"],
          ["29", "30", "31", "", "", "", ""]
        ]
      },
      {
        "header_text": "Februar",
        "cell_count_per_row": 7,
        "row_count": 4,
        "border_style": "border_style_curved_corners",
        "table_content": [
          ["Mo", "Di", "Mi", "Do", "Fr", "Sa", "So"],
          ["1", "2", "3", "4", "5", "6", "7"],
          ["8", "9", "10", "11", "12", "13", "14"],
          ["15", "16", "17", "18", "19", "20", "21"],
          ["22", "23", "24", "25", "26", "27", "28"]
        ]
      },
      {
        "header_text": "März",
        "cell_count_per_row": 7,
        "row_count": 5,
        "border_style": "border_style_curved_corners",
        "table_content": [
          ["Mo", "Di", "Mi", "Do", "Fr", "Sa", "So"],
          ["1", "2", "3", "4", "5", "6", "7"],
          ["8", "9", "10", "11", "12", "13", "14"],
          ["15", "16", "17", "18", "19", "20", "21"],
          ["22", "23", "24", "25", "26", "27", "28"],
          ["29", "30", "31", "", "", "", ""]
        ]
      },
      {
        "header_text": "April",
        "cell_count_per_row": 7,
        "row_count": 5,
        "border_style": "border_style_curved_corners",
        "table_content": [
          ["Mo", "Di", "Mi", "Do", "Fr", "Sa", "So"],
          ["1", "2", "3", "4", "5", "6", "7"],
          ["8", "9", "10", "11", "12", "13", "14"],
          ["15", "16", "17", "18", "19", "20", "21"],
          ["22", "23", "24", "25", "26", "27", "28"],
          ["29", "30", "31", "", "", "", ""]
        ]
      },
      {
        "header_text": "Mai",
        "cell_count_per_row": 7,
        "row_count": 5,
        "border_style": "border_style_curved_corners",
        "table_content": [
          ["Mo", "Di", "Mi", "Do", "Fr", "Sa", "So"],
          ["1", "2", "3", "4", "5", "6", "7"],
          ["8", "9", "10", "11", "12", "13", "14"],
          ["15", "16", "17", "18", "19", "20", "21"],
          ["22", "23", "24", "25", "26", "27", "28"],
          ["29", "30", "31", "", "", "", ""]
        ]
      },
      {
        "header_text": "Juni",
        "cell_count_per_row": 7,
        "row_count": 5,
        "border_style": "border_style_curved_corners",
        "table_content": [
          ["Mo", "Di", "Mi", "Do", "Fr", "Sa", "So"],
          ["1", "2", "3", "4", "5", "6", "7"],
          ["8", "9", "10", "11", "12", "13", "14"],
          ["15", "16", "17", "18", "19", "20", "21"],
          ["22", "23", "24", "25", "26", "27", "28"],
          ["29", "30", "", "", "", "", ""]
        ]
      },
      {
        "header_text": "Juli",
        "cell_count_per_row": 7,
        "row_count": 5,
        "border_style": "border_style_curved_corners",
        "table_content": [
          ["Mo", "Di", "Mi", "Do", "Fr", "Sa", "So"],
          ["1", "2", "3", "4", "5", "6", "7"],
          ["8", "9", "10", "11", "12", "13", "14"],
          ["15", "16", "17", "18", "19", "20", "21"],
          ["22", "23", "24", "25", "26", "27", "28"],
          ["29", "30", "31", "", "", "", ""]
        ]
      },
      {
        "header_text": "August",
        "cell_count_per_row": 7,
        "row_count": 5,
        "border_style": "border_style_curved_corners",
        "table_content": [
          ["Mo", "Di", "Mi", "Do", "Fr", "Sa", "So"],
          ["1", "2", "3", "4", "5", "6", "7"],
          ["8", "9", "10", "11", "12", "13", "14"],
          ["15", "16", "17", "18", "19", "20", "21"],
          ["22", "23", "24", "25", "26", "27", "28"],
          ["29", "30", "31", "", "", "", ""]
        ]
      },
      {
        "header_text": "September",
        "cell_count_per_row": 7,
        "row_count": 5,
        "border_style": "border_style_curved_corners",
        "table_content": [
          ["Mo", "Di", "Mi", "Do", "Fr", "Sa", "So"],
          ["1", "2", "3", "4", "5", "6", "7"],
          ["8", "9", "10", "11", "12", "13", "14"],
          ["15", "16", "17", "18", "19", "20", "21"],
          ["22", "23", "24", "25", "26", "27", "28"],
          ["29", "30", "", "", "", "", ""]
        ]
      },
      {
        "header_text": "Oktober",
        "cell_count_per_row": 7,
        "row_count": 5,
        "border_style": "border_style_curved_corners",
        "table_content": [
          ["Mo", "Di", "Mi", "Do", "Fr", "Sa", "So"],
          ["1", "2", "3", "4", "5", "6", "7"],
          ["8", "9", "10", "11", "12", "13", "14"],
          ["15", "16", "17", "18", "19", "20", "21"],
          ["22", "23", "24", "25", "26", "27", "28"],
          ["29", "30", "31", "", "", "", ""]
        ]
      },
      {
        "header_text": "November",
        "cell_count_per_row": 7,
        "row_count": 5,
        "border_style": "border_style_curved_corners",
        "table_content": [
          ["Mo", "Di", "Mi", "Do", "Fr", "Sa", "So"],
          ["1", "2", "3", "4", "5", "6", "7"],
          ["8", "9", "10", "11", "12", "13", "14"],
          ["15", "16", "17", "18", "19", "20", "21"],
          ["22", "23", "24", "25", "26", "27", "28"],
          ["29", "30", "", "", "", "", ""]
        ]
      },
      {
        "header_text": "Dezember",
        "cell_count_per_row": 7,
        "row_count": 5,
        "border_style": "border_style_curved_corners",
        "table_content": [
          ["Mo", "Di", "Mi", "Do", "Fr", "Sa", "So"],
          ["1", "2", "3", "4", "5", "6", "7"],
          ["8", "9", "10", "11", "12", "13", "14"],
          ["15", "16", "17", "18", "19", "20", "21"],
          ["22", "23", "24", "25", "26", "27", "28"],
          ["29", "30", "31", "", "", "", ""]
        ]
      }
    ]
  }
  